appcli/__init__.py
appcli/app.py
appcli/errors.py
appcli/getters.py
appcli/model.py
appcli/utils.py
appcli/configs/__init__.py
appcli/configs/attrs.py
appcli/configs/configs.py
appcli/configs/layers.py
appcli/configs/on_load.py
appcli/params/__init__.py
appcli/params/inherited.py
appcli/params/param.py
appcli/params/toggle.py
appcli-0.25.0.dist-info/LICENSE.txt
appcli-0.25.0.dist-info/WHEEL
appcli-0.25.0.dist-info/METADATA
appcli-0.25.0.dist-info/RECORD
