Metadata-Version: 2.1
Name: appcli
Version: 0.25.0
Summary: An object-oriented framework for command-line apps.
Home-page: https://github.com/kalekundert/appcli
Author: Kale Kundert
Author-email: kale@thekunderts.net
Requires-Python: ~=3.6
Classifier: Programming Language :: Python :: 3
Classifier: License :: OSI Approved :: MIT License
Requires-Dist: autoprop
Requires-Dist: appdirs
Requires-Dist: docopt~=0.6.2
Requires-Dist: mako
Requires-Dist: more_itertools
Requires-Dist: nestedtext
Requires-Dist: pyyaml
Requires-Dist: tidyexc
Requires-Dist: tomli
Requires-Dist: sphinx ; extra == "docs"
Requires-Dist: sphinx_rtd_theme ; extra == "docs"
Requires-Dist: autoclasstoc ; extra == "docs"
Requires-Dist: pytest ; extra == "tests"
Requires-Dist: pytest-cov ; extra == "tests"
Requires-Dist: coveralls ; extra == "tests"
Requires-Dist: parametrize_from_file ; extra == "tests"
Requires-Dist: voluptuous ; extra == "tests"
Requires-Dist: re-assert ; extra == "tests"
Project-URL: Bug Tracker, https://github.com/kalekundert/appcli/issues
Project-URL: Continuous Integration, https://github.com/kalekundert/appcli/actions
Project-URL: Documentation, https://appcli.readthedocs.io/en/latest/
Project-URL: Test Coverage, https://coveralls.io/github/kalekundert/appcli
Project-URL: Version Control, https://github.com/kalekundert/appcli
Provides-Extra: docs
Provides-Extra: tests
